sdypy_sep005/__init__.py
sdypy_sep005/sep005.py
sdypy_sep005-0.1.1.dist-info/METADATA
sdypy_sep005-0.1.1.dist-info/WHEEL
sdypy_sep005-0.1.1.dist-info/top_level.txt
sdypy_sep005-0.1.1.dist-info/RECORD
