Metadata-Version: 2.1
Name: sdypy_sep005
Version: 0.1.1
Summary: Checks compability with the SDyPy SEP005 guidelines
Home-page: https://github.com/sdypy
Author: Wout Weijtjens
Author-email: wout.weijtjens@vub.be
Maintainer: Wout Weijtjens
Maintainer-email: wout.weijtjens@vub.be
License: MIT license
Keywords: io,tdms,SEP5
Classifier: Development Status :: 3 - Alpha
Classifier: Intended Audience :: Developers
Classifier: Programming Language :: Python :: 3.6
